mamonutils/__init__.py
mamonutils/db.py
mamonutils/image_dimensions.py
mamon_utils-0.1.0.dist-info/METADATA
mamon_utils-0.1.0.dist-info/WHEEL
mamon_utils-0.1.0.dist-info/RECORD
