Metadata-Version: 2.1
Name: mamon-utils
Version: 0.1.0
Summary: Common Mamon11 tools and utilities
Author: WessCoby
Author-email: wc@wesscoby.com
Requires-Python: >=3.8,<4.0
Classifier: Programming Language :: Python :: 3
Classifier: Programming Language :: Python :: 3.8
Classifier: Programming Language :: Python :: 3.9
Classifier: Programming Language :: Python :: 3.10
Classifier: Programming Language :: Python :: 3.11
Requires-Dist: pillow (>=10.0.0,<11.0.0)
Requires-Dist: psycopg2-binary (==2.9.5)
Requires-Dist: python-dotenv (==1.0.0)
Requires-Dist: requests (>=2.31.0,<3.0.0)
